onshape_xblock/__init__.py
onshape_xblock/check_base.py
onshape_xblock/check_context.py
onshape_xblock/check_imports.py
onshape_xblock/checker.py
onshape_xblock/fields.py
onshape_xblock/generate_json_schema.py
onshape_xblock/onshape_xblock_entry.py
onshape_xblock/serialize.py
onshape_xblock/utility.py
onshape_xblock/checks/__init__.py
onshape_xblock/checks/__init__.pyc
onshape_xblock/checks/check_center_of_mass.py
onshape_xblock/checks/check_center_of_mass.pyc
onshape_xblock/checks/check_configuration.py
onshape_xblock/checks/check_configuration.pyc
onshape_xblock/checks/check_element_type.py
onshape_xblock/checks/check_element_type.pyc
onshape_xblock/checks/check_feature_list.py
onshape_xblock/checks/check_feature_list.pyc
onshape_xblock/checks/check_mass.py
onshape_xblock/checks/check_mass.pyc
onshape_xblock/checks/check_part_count.py
onshape_xblock/checks/check_part_count.pyc
onshape_xblock/checks/check_test.py
onshape_xblock/checks/check_test.pyc
onshape_xblock/checks/check_volume.py
onshape_xblock/checks/check_volume.pyc
onshape_xblock/checks/__pycache__/check_test.cpython-27-PYTEST.pyc
onshape_xblock/public/.DS_Store
onshape_xblock/public/__init__.py
onshape_xblock/public/__init__.pyc
onshape_xblock/public/img/correct-icon.png
onshape_xblock/public/img/incorrect-icon.png
onshape_xblock/public/img/unanswered-icon.png
onshape_xblock/public/json/__init__.py
onshape_xblock/public/json/__init__.pyc
onshape_xblock/public/json/check_list_form.json
onshape_xblock/public/json/check_list_form_template.json
onshape_xblock/public/json/test_form.json
onshape_xblock/static/README.txt
onshape_xblock/static/js/inject_vars.js
onshape_xblock/static/js/dist/oauth_login_view.js
onshape_xblock/static/js/dist/student_view.js
onshape_xblock/static/js/dist/studio_view.js
onshape_xblock/static/js/src/oauth_login_view.ts
onshape_xblock/static/js/src/student_view.ts
onshape_xblock/static/js/src/studio_view.ts
onshape_xblock/static/js/src/studio_view.tsx
onshape_xblock-0.0.44.dist-info/METADATA
onshape_xblock-0.0.44.dist-info/WHEEL
onshape_xblock-0.0.44.dist-info/entry_points.txt
onshape_xblock-0.0.44.dist-info/top_level.txt
onshape_xblock-0.0.44.dist-info/RECORD
