Metadata-Version: 2.1
Name: onshape-xblock
Version: 0.0.44
Summary: The Onshape Xblock used to grade Onshape elements according to a number of criteria.
Home-page: UNKNOWN
Author: UNKNOWN
Author-email: UNKNOWN
License: MIT
Platform: UNKNOWN
Requires-Dist: utils
Requires-Dist: xblock
Requires-Dist: xblock-utils
Requires-Dist: pathlib
Requires-Dist: pint
Requires-Dist: jsonpickle
Requires-Dist: onshape-client
Requires-Dist: django
Requires-Dist: jinja2
Requires-Dist: ruamel.yaml
Requires-Dist: uncertainties
Requires-Dist: importlib-resources
